pychanlun/__init__.py
pychanlun/chan.py
pychanlun/fractal.py
pychanlun/pivot.py
pychanlun/segment.py
pychanlun/signal.py
pychanlun/stick.py
pychanlun/stock.py
pychanlun/stroke.py
pychanlun-0.1.7.dist-info/licenses/LICENSE
pychanlun-0.1.7.dist-info/METADATA
pychanlun-0.1.7.dist-info/WHEEL
pychanlun-0.1.7.dist-info/top_level.txt
pychanlun-0.1.7.dist-info/RECORD
