Metadata-Version: 2.4
Name: PyChanLun
Version: 0.1.7
Summary: Applying the Chan Theory (Chan Lun) to analyze stock trading information.
Author-email: Chantu <team@chantu.app>
License-Expression: MIT
Project-URL: Homepage, https://github.com/chanchanapp/pychanlun
Project-URL: Repository, https://github.com/chanchanapp/pychanlun
Project-URL: Bug Tracker, https://github.com/chanchanapp/pychanlun/issues
Classifier: Development Status :: 4 - Beta
Classifier: Intended Audience :: Developers
Classifier: Programming Language :: Python :: 3
Classifier: Programming Language :: Python :: 3.12
Requires-Python: >=3.12
License-File: LICENSE
Requires-Dist: numpy
Requires-Dist: pandas
Dynamic: license-file
